<?xml version="1.0" encoding="UTF-8"?>

<root page="002v" image="https://archive.org/download/ldpd_11728201_000/ldpd_11728201_000_images.zip/ldpd_11728201_000_00000006.tif">
    
    <div id="p002v_1" categories="eye">
        <head language="owy">A good <bp>clearing for the eyes</bp>:</head>
        <ab language="owy">
            Take <m><jit>tuzia <voc>parparta</voc> (perhaps some sort of Tutty? Parpata is an Indian plant?)</jit></m> and <pl><jit><voc>aloer mira (aloe vera?)</voc></jit></pl> <m><jit><voc>toris(???)</voc></jit></m> and <jit><voc>aneh(?)</voc></jit> from <ms>every two drmi(???)</ms> and (???) and mix it all together and <md>put it in the <bp>eye</bp></md>.  So will he be healed, certainly. 
        </ab> 
    </div>
    
    <div id="p002v_2" categories="eye">
        <head language="owy"><md>Another good clearing to clear/lighten</md></head>
        <ab language="owy">
            Take <m><jit>tuzia <voc>parparta</voc> (perhaps some sort of Tutty? Parpata is an Indian plant?)</jit></m>, <pl><ms>two ounces and a half ounce</ms> canapar(??? cinnabar?)</pl>, <m><ms>and a lot [about an ounce?] <heb>and a half</heb></ms> of rose water</m>, <m><ms>and as much(?)</ms> white <heb>wine</heb></m>, and <md>mix it all together very fully and <bp>put it in the eye</bp>.</md>  So will he be healed, certainly. 
        </ab>
    </div>
    
    <div id="p002v_3" categories="eye">
        <ab language="owy">
            <incipit>Another clearing</incipit>: take [the] <pl>root of fennel</pl> and the <pl>root of <jit><voc>peytersen(?)</voc></jit></pl> <m>and mill/grind(???) and crush it and take juice from it</m> and <md>when he wants to go to sleep, he must put(?) <ms>three drops</ms> <bp>in(???) the eye</bp></md>. So will he [be] healed, certainly.
        </ab>        
    </div>
    
</root>